libodb/__init__.py
libodb/client.py
libodb-1.0.1.dist-info/LICENSE
libodb-1.0.1.dist-info/WHEEL
libodb-1.0.1.dist-info/METADATA
libodb-1.0.1.dist-info/RECORD
