Metadata-Version: 2.1
Name: libodb
Version: 1.0.1
Summary: A client library for accessing the OpenDiscordBots API
Home-page: https://github.com/OpenDiscordBots/libodb
License: MIT
Author: vcokltfre
Author-email: vcokltfre@gmail.com
Requires-Python: >=3.8,<4.0
Classifier: License :: OSI Approved :: MIT License
Classifier: Programming Language :: Python :: 3
Classifier: Programming Language :: Python :: 3.10
Classifier: Programming Language :: Python :: 3.8
Classifier: Programming Language :: Python :: 3.9
Requires-Dist: aiohttp (>=3.8.1,<4.0.0)
Requires-Dist: pydantic (>=1.9.0,<2.0.0)
Project-URL: Repository, https://github.com/OpenDiscordBots/libodb
